servehub/__about__.py
servehub/__init__.py
servehub/client.py
servehub/exceptions.py
servehub-0.1.1.dist-info/LICENSE
servehub-0.1.1.dist-info/METADATA
servehub-0.1.1.dist-info/WHEEL
servehub-0.1.1.dist-info/top_level.txt
servehub-0.1.1.dist-info/RECORD
