Metadata-Version: 2.1
Name: servehub
Version: 0.1.1
Summary: Python client for ServeHub
Author: ServeHub, Inc.
License: 
Project-URL: homepage, https://servehub.co/
Project-URL: repository, https://github.com/serve-hub/servehub-python
Requires-Python: >=3.8
License-File: LICENSE
Requires-Dist: packaging
Requires-Dist: pydantic >1
Requires-Dist: requests >2
Provides-Extra: dev
Requires-Dist: black ; extra == 'dev'
Requires-Dist: mypy ; extra == 'dev'
Requires-Dist: pytest ; extra == 'dev'
Requires-Dist: responses ; extra == 'dev'
Requires-Dist: ruff ; extra == 'dev'
